grade_conversion_calculator/VERSION
grade_conversion_calculator/__init__.py
grade_conversion_calculator/urls.py
grade_conversion_calculator/views.py
grade_conversion_calculator/locale/en_US/LC_MESSAGES/djangojs.mo
grade_conversion_calculator/locale/en_US/LC_MESSAGES/djangojs.po
grade_conversion_calculator/static/grade_conversion_calculator/css/desktop.less
grade_conversion_calculator/static/grade_conversion_calculator/css/mobile.less
grade_conversion_calculator/static/grade_conversion_calculator/img/fa-caret-down3.png
grade_conversion_calculator/static/grade_conversion_calculator/js/handlebars-i18n.js
grade_conversion_calculator/static/grade_conversion_calculator/js/main.js
grade_conversion_calculator/static/grade_conversion_calculator/js/vendor/handlebars-1.0.0.min.js
grade_conversion_calculator/static/grade_conversion_calculator/js/vendor/less-1.7.0.min.js
grade_conversion_calculator/templates/demo.html
grade_conversion_calculator/templates/grade_conversion_calculator/handlebars/calculator_addrow.html
grade_conversion_calculator/templates/grade_conversion_calculator/handlebars/calculator_row.html
grade_conversion_calculator/templates/grade_conversion_calculator/handlebars/converter.html
grade_conversion_calculator/templates/grade_conversion_calculator/handlebars/grade_scale_row.html
grade_conversion_calculator/tests/__init__.py
grade_conversion_calculator/tests/test_views.py
UW_Grade_Conversion_Calculator-1.4.2.dist-info/LICENSE
UW_Grade_Conversion_Calculator-1.4.2.dist-info/METADATA
UW_Grade_Conversion_Calculator-1.4.2.dist-info/WHEEL
UW_Grade_Conversion_Calculator-1.4.2.dist-info/top_level.txt
UW_Grade_Conversion_Calculator-1.4.2.dist-info/RECORD
