Metadata-Version: 2.1
Name: UW-Grade-Conversion-Calculator
Version: 1.4.2
Summary: UW Grade Scale Conversion Calculator application
Home-page: https://github.com/uw-it-aca/grade-conversion-calculator
Author: UW-IT T&LS
Author-email: aca-it@uw.edu
License: Apache License, Version 2.0
Classifier: Intended Audience :: Developers
Classifier: License :: OSI Approved :: Apache Software License
Classifier: Operating System :: OS Independent
Classifier: Programming Language :: Python
License-File: LICENSE
Requires-Dist: Django <5,>=4.2
